eve_jwt/__init__.py
eve_jwt/auth.py
eve_jwt/validation.py
eve_jwt-0.1.10.dist-info/LICENSE
eve_jwt-0.1.10.dist-info/WHEEL
eve_jwt-0.1.10.dist-info/METADATA
eve_jwt-0.1.10.dist-info/RECORD
