Metadata-Version: 2.1
Name: eve-jwt
Version: 0.1.10
Summary: Top-level package for eve-jwt.
Home-page: https://github.com/jmosbacher/eve_jwt
License: MIT
Author: Yossi Mosbacher
Author-email: joe.mosbacher@gmail.com
Requires-Python: >=3.6
Classifier: Development Status :: 2 - Pre-Alpha
Classifier: Intended Audience :: Developers
Classifier: License :: OSI Approved :: MIT License
Classifier: Natural Language :: English
Classifier: Programming Language :: Python :: 3
Classifier: Programming Language :: Python :: 3.6
Classifier: Programming Language :: Python :: 3.7
Classifier: Programming Language :: Python :: 3.8
Requires-Dist: Authlib (>=0.15.2,<0.16.0)
Requires-Dist: eve (>=1.1.4,<2.0.0)
Requires-Dist: flask (>=1.1.2,<2.0.0)
Requires-Dist: requests (>=2.25.0,<3.0.0)
